fds/__init__.py
fds/sdk/__init__.py
fds/sdk/IntradayTickHistory/__init__.py
fds/sdk/IntradayTickHistory/api_client.py
fds/sdk/IntradayTickHistory/configuration.py
fds/sdk/IntradayTickHistory/exceptions.py
fds/sdk/IntradayTickHistory/model_utils.py
fds/sdk/IntradayTickHistory/rest.py
fds/sdk/IntradayTickHistory/api/__init__.py
fds/sdk/IntradayTickHistory/api/first_trade_api.py
fds/sdk/IntradayTickHistory/api/last_trade_api.py
fds/sdk/IntradayTickHistory/api/quote_at_time_api.py
fds/sdk/IntradayTickHistory/api/tick_history_api.py
fds/sdk/IntradayTickHistory/api/trades_at_time_api.py
fds/sdk/IntradayTickHistory/apis/__init__.py
fds/sdk/IntradayTickHistory/model/__init__.py
fds/sdk/IntradayTickHistory/model/fields.py
fds/sdk/IntradayTickHistory/model/intervals.py
fds/sdk/IntradayTickHistory/model/specialfield.py
fds/sdk/IntradayTickHistory/model/tickhistory_response.py
fds/sdk/IntradayTickHistory/models/__init__.py
fds.sdk.IntradayTickHistory-0.20.0.dist-info/LICENSE
fds.sdk.IntradayTickHistory-0.20.0.dist-info/METADATA
fds.sdk.IntradayTickHistory-0.20.0.dist-info/WHEEL
fds.sdk.IntradayTickHistory-0.20.0.dist-info/top_level.txt
fds.sdk.IntradayTickHistory-0.20.0.dist-info/RECORD
